{"version":"0.1.0","name":"proofpitch","instructions":[{"name":"createMarket","accounts":[{"name":"creator","isMut":true,"isSigner":true},{"name":"market","isMut":true,"isSigner":false},{"name":"systemProgram","isMut":false,"isSigner":false}],"args":[{"name":"id","type":"u64"},{"name":"fixtureId","type":"i64"},{"name":"statKeyA","type":"u32"},{"name":"statKeyB","type":"u32"},{"name":"op","type":"u8"},{"name":"cmp","type":"u8"},{"name":"threshold","type":"i32"},{"name":"lockTs","type":"i64"},{"name":"label","type":"string"}]},{"name":"join","accounts":[{"name":"user","isMut":true,"isSigner":true},{"name":"market","isMut":true,"isSigner":false},{"name":"position","isMut":true,"isSigner":false},{"name":"systemProgram","isMut":false,"isSigner":false}],"args":[{"name":"side","type":"u8"},{"name":"amount","type":"u64"}]},{"name":"settle","accounts":[{"name":"market","isMut":true,"isSigner":false},{"name":"dailyScoresMerkleRoots","isMut":false,"isSigner":false},{"name":"txoracleProgram","isMut":false,"isSigner":false}],"args":[{"name":"side","type":"u8"},{"name":"ts","type":"i64"},{"name":"summary","type":{"defined":"ScoresBatchSummary"}},{"name":"fixtureProof","type":{"vec":{"defined":"ProofNode"}}},{"name":"mainTreeProof","type":{"vec":{"defined":"ProofNode"}}},{"name":"predicate","type":{"defined":"TraderPredicate"}},{"name":"statA","type":{"defined":"StatTerm"}},{"name":"statB","type":{"option":{"defined":"StatTerm"}}},{"name":"op","type":{"option":{"defined":"BinaryExpression"}}}]},{"name":"voidMarket","accounts":[{"name":"market","isMut":true,"isSigner":false}],"args":[]},{"name":"claim","accounts":[{"name":"user","isMut":true,"isSigner":true},{"name":"market","isMut":true,"isSigner":false},{"name":"position","isMut":true,"isSigner":false}],"args":[]}],"accounts":[{"name":"Market","type":{"kind":"struct","fields":[{"name":"creator","type":"publicKey"},{"name":"id","type":"u64"},{"name":"fixtureId","type":"i64"},{"name":"statKeyA","type":"u32"},{"name":"statKeyB","type":"u32"},{"name":"op","type":"u8"},{"name":"cmp","type":"u8"},{"name":"threshold","type":"i32"},{"name":"lockTs","type":"i64"},{"name":"yesPool","type":"u64"},{"name":"noPool","type":"u64"},{"name":"state","type":"u8"},{"name":"settledTs","type":"i64"},{"name":"proofTs","type":"i64"},{"name":"label","type":"string"},{"name":"bump","type":"u8"}]}},{"name":"Position","type":{"kind":"struct","fields":[{"name":"market","type":"publicKey"},{"name":"owner","type":"publicKey"},{"name":"side","type":"u8"},{"name":"amount","type":"u64"},{"name":"claimed","type":"bool"},{"name":"bump","type":"u8"}]}}],"types":[{"name":"ProofNode","type":{"kind":"struct","fields":[{"name":"hash","type":{"array":["u8",32]}},{"name":"isRightSibling","type":"bool"}]}},{"name":"ScoreStat","type":{"kind":"struct","fields":[{"name":"key","type":"u32"},{"name":"value","type":"i32"},{"name":"period","type":"i32"}]}},{"name":"ScoresUpdateStats","type":{"kind":"struct","fields":[{"name":"updateCount","type":"i32"},{"name":"minTimestamp","type":"i64"},{"name":"maxTimestamp","type":"i64"}]}},{"name":"ScoresBatchSummary","type":{"kind":"struct","fields":[{"name":"fixtureId","type":"i64"},{"name":"updateStats","type":{"defined":"ScoresUpdateStats"}},{"name":"eventsSubTreeRoot","type":{"array":["u8",32]}}]}},{"name":"StatTerm","type":{"kind":"struct","fields":[{"name":"statToProve","type":{"defined":"ScoreStat"}},{"name":"eventStatRoot","type":{"array":["u8",32]}},{"name":"statProof","type":{"vec":{"defined":"ProofNode"}}}]}},{"name":"TraderPredicate","type":{"kind":"struct","fields":[{"name":"threshold","type":"i32"},{"name":"comparison","type":{"defined":"Comparison"}}]}},{"name":"Comparison","type":{"kind":"enum","variants":[{"name":"GreaterThan"},{"name":"LessThan"},{"name":"EqualTo"}]}},{"name":"BinaryExpression","type":{"kind":"enum","variants":[{"name":"Add"},{"name":"Subtract"}]}}],"errors":[{"code":6000,"name":"LabelTooLong","msg":"label longer than 64 bytes"},{"code":6001,"name":"BadSpec","msg":"invalid market spec"},{"code":6002,"name":"BadSide","msg":"side must be 1 (YES) or 2 (NO)"},{"code":6003,"name":"ZeroStake","msg":"stake must be positive"},{"code":6004,"name":"MarketClosed","msg":"market is not open"},{"code":6005,"name":"MarketLocked","msg":"market is locked (kickoff passed)"},{"code":6006,"name":"WrongFixture","msg":"proof is for a different fixture"},{"code":6007,"name":"WrongStat","msg":"proof stat does not match the market spec or is not the finalised record"},{"code":6008,"name":"PredicateMismatch","msg":"predicate does not match the market (or its negation for NO)"},{"code":6009,"name":"WrongRootsAccount","msg":"daily roots account is not the canonical txoracle PDA for that day"},{"code":6010,"name":"NoOracleAnswer","msg":"oracle returned no answer"},{"code":6011,"name":"ProofSaysNo","msg":"the proof does not make this side's predicate true"},{"code":6012,"name":"TooEarlyToVoid","msg":"too early to void — settlement window still open"},{"code":6013,"name":"NotSettled","msg":"market not settled yet"},{"code":6014,"name":"LosingSide","msg":"position is on the losing side"},{"code":6015,"name":"AlreadyClaimed","msg":"already claimed"},{"code":6016,"name":"WrongMarket","msg":"position does not belong to this market"},{"code":6017,"name":"NotYourPosition","msg":"position owned by someone else"},{"code":6018,"name":"Overflow","msg":"arithmetic overflow"}]}
